pyargon2/__init__.py
pyargon2/_argon2.abi3.so
pyargon2/_compiler.py
pyargon2/argon2.py
pyargon2/classes/__init__.py
pyargon2/classes/errors.py
pyargon2-1.0.7.dist-info/LICENSE
pyargon2-1.0.7.dist-info/METADATA
pyargon2-1.0.7.dist-info/WHEEL
pyargon2-1.0.7.dist-info/top_level.txt
pyargon2-1.0.7.dist-info/RECORD
