Metadata-Version: 2.1
Name: pyargon2
Version: 1.0.7
Summary: Simultaneously the simplest and most powerful Argon2 implemenation in Python
Author-email: James Webb <james@ultra-horizon.com>
License: Apache2
Project-URL: Homepage, https://github.com/ultrahorizon/pyargon2
Project-URL: Bug Tracker, https://github.com/ultrahorizon/pyargon2/issues
Keywords: argon2,hash,password
Classifier: Development Status :: 5 - Production/Stable
Classifier: Intended Audience :: Developers
Classifier: License :: OSI Approved :: Apache Software License
Classifier: Operating System :: MacOS
Classifier: Operating System :: Microsoft :: Windows
Classifier: Operating System :: POSIX
Classifier: Operating System :: Unix
Classifier: Programming Language :: Python :: 3
Classifier: Topic :: Security
Classifier: Topic :: Security :: Cryptography
Classifier: Topic :: Software Development :: Libraries
Requires-Python: >=3.9
License-File: LICENSE
Requires-Dist: cffi (>=1.0.0)
